pymainprocess-0.1.3.dist-info/METADATA
pymainprocess-0.1.3.dist-info/WHEEL
pymainprocess.libs/libgcc_s-b5472b99.so.1
pymainprocess/child.py
pymainprocess/plugin.py
pymainprocess/__init__.py
pymainprocess/pymainprocess.cpython-39-i386-linux-gnu.so
pymainprocess-0.1.3.dist-info/RECORD
