Metadata-Version: 2.3
Name: pymainprocess
Version: 0.1.3
Classifier: Programming Language :: Rust
Classifier: Programming Language :: Python :: Implementation :: CPython
Classifier: Programming Language :: Python :: Implementation :: PyPy
Summary: Python Process Module, written in Python and Rust
Author: Kevin Alexander Krefting <kevin@krefting.com>
Author-email: Kevin Alexander Krefting <kakrefting@gmail.com>
License: MIT
Requires-Python: >=3.8
